rendakun/__init__.py
rendakun/py.typed
rendakun-0.0.1.dist-info/entry_points.txt
rendakun-0.0.1.dist-info/LICENSE.txt
rendakun-0.0.1.dist-info/METADATA
rendakun-0.0.1.dist-info/WHEEL
rendakun-0.0.1.dist-info/RECORD
